setup.py
mvs_client/MVS_Client.py
mvs_client/__init__.py
mvs_client.egg-info/PKG-INFO
mvs_client.egg-info/SOURCES.txt
mvs_client.egg-info/dependency_links.txt
mvs_client.egg-info/requires.txt
mvs_client.egg-info/top_level.txt